pyscape/__init__.py
pyscape/api.py
pyscape/defaults.py
pyscape/endpoints.py
pyscape/fields.py
pyscape_client-2015.03.dist-info/DESCRIPTION.rst
pyscape_client-2015.03.dist-info/METADATA
pyscape_client-2015.03.dist-info/metadata.json
pyscape_client-2015.03.dist-info/RECORD
pyscape_client-2015.03.dist-info/top_level.txt
pyscape_client-2015.03.dist-info/WHEEL
