Metadata-Version: 2.0
Name: pyscape-client
Version: 2015.03
Summary: Facilitate grabbing data from Moz API.
Home-page: https://github.com/benjaminestes/pyscape
Author: Benjamin Estes
Author-email: benjamin.estes@distilled.net
License: MIT
Keywords: moz linkscape
Platform: UNKNOWN
Classifier: Development Status :: 4 - Beta
Classifier: Intended Audience :: Developers
Classifier: License :: OSI Approved :: MIT License
Classifier: Programming Language :: Python :: 3.4
Requires-Dist: requests
